mycustomtest/__init__.py
mycustomtest/main.py
mycustomtest-0.1.1.dist-info/entry_points.txt
mycustomtest-0.1.1.dist-info/WHEEL
mycustomtest-0.1.1.dist-info/METADATA
mycustomtest-0.1.1.dist-info/RECORD
