Metadata-Version: 2.1
Name: mycustomtest
Version: 0.1.1
Summary: 
Author: mycustomtest
Author-email: mycustomtest@example.com
Requires-Python: >=3.10,<4.0
Classifier: Programming Language :: Python :: 3
Classifier: Programming Language :: Python :: 3.10
Requires-Dist: typer[all] (>=0.6.1,<0.7.0)
